picnik_integrator/__init__.py
picnik_integrator/picnik_integrator.py
picnik_integrator-0.2.1.dist-info/LICENSE
picnik_integrator-0.2.1.dist-info/WHEEL
picnik_integrator-0.2.1.dist-info/METADATA
picnik_integrator-0.2.1.dist-info/RECORD
